pywebcapture/__init__.py
pywebcapture/driver.py
pywebcapture/loader.py
pywebcapture-0.0.3.dist-info/LICENSE
pywebcapture-0.0.3.dist-info/METADATA
pywebcapture-0.0.3.dist-info/WHEEL
pywebcapture-0.0.3.dist-info/top_level.txt
pywebcapture-0.0.3.dist-info/RECORD
