Metadata-Version: 2.1
Name: pywebcapture
Version: 0.0.3
Summary: A package that allows users to capture full-page screenshots of websites using Selenium and Chrome webdriver.
Home-page: https://github.com/wirelessfuture/pywebcapture
Author: Christopher Andrews
Author-email: wirelessfuture2000@gmail.com
License: UNKNOWN
Platform: UNKNOWN
Classifier: Programming Language :: Python :: 3
Classifier: License :: Freeware
Classifier: Operating System :: OS Independent
Requires-Python: >=3.8
Requires-Dist: selenium
